flake8_idom_hooks/__init__.py
flake8_idom_hooks/common.py
flake8_idom_hooks/exhaustive_deps.py
flake8_idom_hooks/flake8_plugin.py
flake8_idom_hooks/rules_of_hooks.py
flake8_idom_hooks/run.py
flake8_idom_hooks-0.6.4.dist-info/LICENSE
flake8_idom_hooks-0.6.4.dist-info/METADATA
flake8_idom_hooks-0.6.4.dist-info/WHEEL
flake8_idom_hooks-0.6.4.dist-info/entry_points.txt
flake8_idom_hooks-0.6.4.dist-info/top_level.txt
flake8_idom_hooks-0.6.4.dist-info/RECORD
