Metadata-Version: 2.1
Name: flake8-idom-hooks
Version: 0.6.4
Summary: Flake8 plugin to enforce the rules of hooks for IDOM
Home-page: https://github.com/idom-team/flake8-idom-hooks
Author: Ryan Morshead
Author-email: ryan.morshead@gmail.com
License: MIT
Platform: Linux
Platform: Mac OS X
Platform: Windows
Classifier: Environment :: Console
Classifier: Framework :: Flake8
Classifier: Intended Audience :: Developers
Classifier: License :: OSI Approved :: MIT License
Classifier: Operating System :: OS Independent
Classifier: Programming Language :: Python
Classifier: Topic :: Software Development :: Libraries :: Python Modules
Classifier: Topic :: Software Development :: Quality Assurance
Requires-Python: >=3.6
License-File: LICENSE
Requires-Dist: flake8 (>=3.7)
Requires-Dist: black
